odoo/addons/shopinvader_product_order/README.rst
odoo/addons/shopinvader_product_order/__init__.py
odoo/addons/shopinvader_product_order/__manifest__.py
odoo/addons/shopinvader_product_order/data/ir_export_product.xml
odoo/addons/shopinvader_product_order/i18n/shopinvader_product_order.pot
odoo/addons/shopinvader_product_order/models/__init__.py
odoo/addons/shopinvader_product_order/models/shopinvader_product.py
odoo/addons/shopinvader_product_order/models/shopinvader_variant.py
odoo/addons/shopinvader_product_order/readme/CONTRIBUTORS.rst
odoo/addons/shopinvader_product_order/readme/DESCRIPTION.rst
odoo/addons/shopinvader_product_order/static/description/index.html
odoo/addons/shopinvader_product_order/views/shopinvader_product.xml
odoo14_addon_shopinvader_product_order-14.0.1.1.0.dist-info/METADATA
odoo14_addon_shopinvader_product_order-14.0.1.1.0.dist-info/WHEEL
odoo14_addon_shopinvader_product_order-14.0.1.1.0.dist-info/top_level.txt
odoo14_addon_shopinvader_product_order-14.0.1.1.0.dist-info/RECORD
